debouncer/__init__.py
debouncer/app.py
debouncer/config.py
debouncer/dispatch.py
debouncer/router.py
debouncer/schema.py
debouncer/state.py
debouncer/store.py
web/dist/assets/index.178de123.css
web/dist/assets/index.dc29a0fd.js
web/dist/assets/vendor.ce87bf07.js
web/dist/index.html
web/dist/robots.txt
debouncer-0.0.8.dist-info/LICENSE
debouncer-0.0.8.dist-info/WHEEL
debouncer-0.0.8.dist-info/METADATA
debouncer-0.0.8.dist-info/RECORD
