Metadata-Version: 2.1
Name: debouncer
Version: 0.0.8
Summary: Debouncer is a proxy that debounce requests.
Author: Joola
Author-email: jooola@users.noreply.github.com
Requires-Python: >=3.7,<4.0
Classifier: Development Status :: 3 - Alpha
Classifier: License :: OSI Approved :: GNU General Public License v3 (GPLv3)
Classifier: Programming Language :: Python
Classifier: Programming Language :: Python :: 3
Classifier: Programming Language :: Python :: 3.10
Classifier: Programming Language :: Python :: 3.7
Classifier: Programming Language :: Python :: 3.8
Classifier: Programming Language :: Python :: 3.9
Requires-Dist: fastapi (>=0.70.1,<0.71.0)
Requires-Dist: httpx (>=0.21.1,<0.22.0)
Requires-Dist: loguru (>=0.5.3,<0.6.0)
Requires-Dist: pydantic (>=1.8.2,<2.0.0)
Requires-Dist: sqlitedict (>=1.7.0,<2.0.0)
Requires-Dist: uvicorn (>=0.16.0,<0.17.0)
